README.md
setup.cfg
setup.py
automl_pn/_init_.py
automl_pn/binary_classifier.py
automl_pn.egg-info/PKG-INFO
automl_pn.egg-info/SOURCES.txt
automl_pn.egg-info/dependency_links.txt
automl_pn.egg-info/not-zip-safe
automl_pn.egg-info/requires.txt
automl_pn.egg-info/top_level.txt
automl_pn/utils/metrics.py
automl_pn/utils/models.py
automl_pn/utils/preprocessor.py