Metadata-Version: 2.1
Name: automl-pn
Version: 0.1.3
Summary: Automated binary classification
Home-page: https://github.com/CTPAHH1K/auto-binary-classifier
Author: Maxim
Author-email: maximponomarev92@gmail.com
License: UNKNOWN
Platform: UNKNOWN
Classifier: Programming Language :: Python :: 3
Classifier: License :: OSI Approved :: MIT License
Classifier: Operating System :: OS Independent
Requires-Python: >= 3.7
